README.md
SolveEquation.py
disolv.py
setup.cfg
setup.py
disolv.egg-info/PKG-INFO
disolv.egg-info/SOURCES.txt
disolv.egg-info/dependency_links.txt
disolv.egg-info/requires.txt
disolv.egg-info/top_level.txt